anypath/__init__.py
anypath/anypath.py
anypath/dependencies.py
anypath/pathprovider/__init__.py
anypath/pathprovider/git.py
anypath/pathprovider/http.py
anypath/pathprovider/local.py
anypath/pathprovider/mercurial.py
anypath/pathprovider/sftp.py
anypath-1.0.0.dist-info/DESCRIPTION.rst
anypath-1.0.0.dist-info/METADATA
anypath-1.0.0.dist-info/RECORD
anypath-1.0.0.dist-info/WHEEL
anypath-1.0.0.dist-info/metadata.json
anypath-1.0.0.dist-info/top_level.txt
