Metadata-Version: 2.0
Name: anypath
Version: 1.0.0
Summary: AnyPath makes it trivial to fetch remote resources and work with them locally.
Home-page: https://github.com/vaubarth/anypath
Author: Vincent Barth
Author-email: vdbarth@posteo.at
License: Mozilla Public License 2.0 (MPL 2.0)
Platform: UNKNOWN
Classifier: Programming Language :: Python :: 3 :: Only
Classifier: Programming Language :: Python :: 3.6
Classifier: License :: OSI Approved :: Mozilla Public License 2.0 (MPL 2.0)
